kedro_hyperparam/__init__.py
kedro_hyperparam/__main__.py
kedro_hyperparam/py.typed
kedro_hyperparam-0.0.1a0.dist-info/entry_points.txt
kedro_hyperparam-0.0.1a0.dist-info/LICENSE.rst
kedro_hyperparam-0.0.1a0.dist-info/WHEEL
kedro_hyperparam-0.0.1a0.dist-info/METADATA
kedro_hyperparam-0.0.1a0.dist-info/RECORD
