Metadata-Version: 2.1
Name: kedro-hyperparam
Version: 0.0.1a0
Summary: Kedro Hyperparam
Home-page: https://github.com/stasulam/kedro-hyperparam
License: MIT
Author: Lukasz Ambroziak
Author-email: l.ambroziak@protonmail.com
Requires-Python: >=3.6.1,<4.0.0
Classifier: License :: OSI Approved :: MIT License
Classifier: Programming Language :: Python :: 3
Classifier: Programming Language :: Python :: 3.6
Classifier: Programming Language :: Python :: 3.7
Classifier: Programming Language :: Python :: 3.8
Classifier: Programming Language :: Python :: 3.9
Requires-Dist: click (>=7.0,<8.0)
Project-URL: Changelog, https://github.com/stasulam/kedro-hyperparam/releases
Project-URL: Documentation, https://kedro-hyperparam.readthedocs.io
Project-URL: Repository, https://github.com/stasulam/kedro-hyperparam
